{
    "LayerFilter: Add Grain": {
        "title": "噪点",
        "inputs": {
            "image": "图像"
        },
        "widgets": {
            "grain_power": "颗粒强度",
            "grain_scale": "颗粒缩放",
            "grain_sat": "颗粒饱和度"
        },
        "outputs": {
            "image": "图像"
        }
    },
    "LayerFilter: ChannelShake": {
        "title": "通道错位",
        "inputs": {
            "image": "图像"
        },
        "widgets": {
            "distance": "距离",
            "angle": "角度",
            "mode": "模式"
        },
        "outputs": {
            "image": "图像"
        }
    },
    "LayerFilter: ColorMap": {
        "title": "彩色热力图",
        "inputs": {
            "image": "图像"
        },
        "widgets": {
            "color_map": "类型",
            "opacity": "不透明"
        },
        "outputs": {
            "image": "图像"
        }
    },
    "LayerFilter: Film": {
        "title": "胶片颗粒",
        "inputs": {
            "image": "图像",
            "depth_map": "深度图"
        },
        "widgets": {
            "center_x": "中心X",
            "center_y": "中心Y",
            "saturation": "饱和度",
            "vignette_intensity": "暗角强度",
            "grain_power": "颗粒强度",
            "grain_scale": "颗粒缩放",
            "grain_sat": "颗粒饱和度",
            "grain_shadows": "颗粒阴影",
            "grain_highs": "亮部颗粒强度",
            "blur_strength": "模糊强度",
            "blur_focus_spread": "焦点扩散",
            "focal_depth": "模拟虚焦"
        },
        "outputs": {
            "image": "图像"
        }
    },
    "LayerFilter: FilmV2": {
        "title": "胶片颗粒 V2",
        "inputs": {
            "image": "图像",
            "depth_map": "深度图"
        },
        "widgets": {
            "center_x": "中心X",
            "center_y": "中心Y",
            "saturation": "饱和度",
            "vignette_intensity": "暗角强度",
            "grain_method": "颗粒算法",
            "grain_power": "颗粒强度",
            "grain_scale": "颗粒缩放",
            "grain_sat": "颗粒饱和度",
            "filmgrainer_shadows": "颗粒阴影",
            "filmgrainer_highs": "颗粒高光",
            "blur_strength": "模糊强度",
            "blur_focus_spread": "焦点扩散",
            "focal_depth": "模拟虚焦"
        },
        "outputs": {
            "image": "图像"
        }
    },
    "LayerFilter: GaussianBlur": {
        "title": "高斯模糊",
        "inputs": {
            "image": "图像",
            "blur": "模糊"
        },
        "outputs": {
            "image": "图像"
        }
    },
    "LayerFilter: HDREffects": {
        "title": "HDR特效",
        "inputs": {
            "image": "图像"
        },
        "widgets": {
            "hdr_intensity": "HDR强度",
            "shadow_intensity": "阴影强度",
            "highlight_intensity": "高光强度",
            "gamma_intensidi": "伽马强度",
            "contrast": "对比度",
            "enhance_color": "增强颜色"
        },
        "outputs": {
            "image": "图像"
        }
    },
    "LayerFilter: LightLeak": {
        "title": "漏光",
        "inputs": {
            "image": "图像"
        },
        "widgets": {
            "light": "光斑",
            "corner": "位置",
            "hue": "色相",
            "saturation": "饱和度",
            "opacity": "不透明"
        },
        "outputs": {
            "image": "图像"
        }
    },
    "LayerFilter: MotionBlur": {
        "title": "运动模糊",
        "inputs": {
            "image": "图像"
        },
        "widgets": {
            "angle": "角度",
            "blur": "模糊"
        },
        "outputs": {
            "image": "图像"
        }
    },
    "LayerFilter: Sharp & Soft": {
        "title": "锐化/柔化",
        "inputs": {
            "image": "图像"
        },
        "widgets": {
            "enhance": "增强"
        },
        "outputs": {
            "image": "图像"
        }
    },
    "LayerFilter: SharpAndSoft": {
        "title": "锐化/柔化",
        "inputs": {
            "image": "图像"
        },
        "widgets": {
            "enhance": "增强"
        },
        "outputs": {
            "image": "图像"
        }
    },
    "LayerFilter: SkinBeauty": {
        "title": "磨皮",
        "inputs": {
            "image": "图像"
        },
        "widgets": {
            "smooth": "平滑",
            "threshold": "阈值",
            "opacity": "不透明"
        },
        "outputs": {
            "image": "图像",
            "MASK": "遮罩"
        }
    },
    "LayerFilter: SoftLight": {
        "title": "柔光",
        "inputs": {
            "image": "图像"
        },
        "widgets": {
            "soft": "柔和",
            "threshold": "阈值",
            "opacity": "不透明"
        },
        "outputs": {
            "image": "图像"
        }
    },
    "LayerFilter: WaterColor": {
        "title": "水彩",
        "inputs": {
            "image": "图像"
        },
        "widgets": {
            "line_density": "密度",
            "opacity": "不透明"
        },
        "outputs": {
            "image": "图像"
        }
    },


    "LayerColor: ColorAdapter": {
        "title": "颜色适配",
        "inputs": {
            "image": "图像",
            "color_ref_image": "参考图像"
        },
        "widgets": {
            "opacity": "不透明"
        },
        "outputs": {
            "image": "图像"
        }
    },
    "LayerColor: AutoAdjust": {
        "title": "自动调色",
        "inputs": {
            "image": "图像"
        },
        "widgets": {
            "strength": "强度",
            "brightness": "亮度",
            "contrast": "对比度",
            "saturation": "饱和度",
            "red": "红色",
            "green": "绿色",
            "blue": "蓝色"
        },
        "outputs": {
            "image": "图像"
        }
    },
    "LayerColor: AutoAdjustV2": {
        "title": "自动调色 V2",
        "inputs": {
            "image": "图像",
            "mask": "遮罩"
        },
        "widgets": {
            "strength": "强度",
            "brightness": "亮度",
            "contrast": "对比度",
            "saturation": "饱和度",
            "red": "红色",
            "green": "绿色",
            "blue": "蓝色",
            "mode": "模式"
        },
        "outputs": {
            "image": "图像"
        }
    },
    "LayerColor: AutoBrightness": {
        "title": "自动亮度",
        "inputs": {
            "image": "图像",
            "mask": "遮罩"
        },
        "widgets": {
            "strength": "强度",
            "saturation": "饱和度"
        },
        "outputs": {
            "image": "图像"
        }
    },
    "LayerColor: Brightness & Contrast": {
        "title": "亮度/对比度",
        "inputs": {
            "image": "图像"
        },
        "widgets": {
            "brightness": "亮度",
            "contrast": "对比度",
            "saturation": "饱和度"
        },
        "outputs": {
            "image": "图像"
        }
    },
    "LayerColor: ColorBalance": {
        "title": "色彩平衡",
        "inputs": {
            "image": "图像"
        },
        "widgets": {
            "cyan_red": "青-红",
            "megenta_green": "品红-绿",
            "yellow_blue": "黄-蓝"
        },
        "outputs": {
            "image": "图像"
        }
    },
    "LayerColor: ColorTemperature": {
        "title": "色温",
        "inputs": {
            "image": "图像"
        },
        "widgets": {
            "temperature": "温度"
        },
        "outputs": {
            "image": "图像"
        }
    },
    "LayerColor: Exposure": {
        "title": "曝光",
        "inputs": {
            "image": "图像"
        },
        "widgets": {
            "exposure": "曝光"
        },
        "outputs": {
            "image": "图像"
        }
    },
    "LayerColor: Gamma": {
        "title": "Gamma",
        "inputs": {
            "image": "图像"
        },
        "widgets": {
            "gamma": "gamma"
        },
        "outputs": {
            "image": "图像"
        }
    },
    "LayerColor: HSV": {
        "title": "HSV",
        "inputs": {
            "image": "图像"
        },
        "widgets": {
            "H": "H",
            "S": "S",
            "V": "V"
        },
        "outputs": {
            "image": "图像"
        }
    },
    "LayerColor: LAB": {
        "title": "LAB",
        "inputs": {
            "image": "图像"
        },
        "widgets": {
            "L": "L",
            "A": "A",
            "B": "B"
        },
        "outputs": {
            "image": "图像"
        }
    },
    "LayerColor: Levels": {
        "title": "色阶",
        "inputs": {
            "image": "图像"
        },
        "widgets": {
            "channel": "通道",
            "black_point": "黑色阈值",
            "white_point": "白色阈值",
            "gray_point": "灰色阈值",
            "output_black_point": "输出黑色阈值",
            "output_white_point": "输出白色阈值"
        },
        "outputs": {
            "image": "图像"
        }
    },
    "LayerColor: LUT Apply": {
      "title": "LUT应用",
        "inputs": {
            "image": "图像"
        },
        "widgets": {
            "LUT": "LUT",
            "color_space": "色彩空间"
        },
        "outputs": {
            "image": "图像"
        }
    },
    "LayerColor: RGB": {
        "title": "RGB",
        "inputs": {
            "image": "图像"
        },
        "widgets": {
            "R": "R",
            "G": "G",
            "B": "B"
        },
        "outputs": {
            "image": "图像"
        }
    },
    "LayerColor: Color of Shadow & Highlight": {
        "title": "阴影与高光",
        "inputs": {
            "image": "图像",
            "mask": "遮罩"
        },
        "widgets": {
            "shadow_brightness": "阴影亮度",
            "shadow_saturation": "阴影饱和度",
            "shadow_hue": "阴影色相",
            "shadow_level_offset": "阴影强度",
            "shadow_range": "阴影范围",
            "highlight_brightness": "高光亮度",
            "highlight_saturation": "高光饱和度",
            "highlight_hue": "高光色相",
            "highlight_level_offset": "高光强度",
            "highlight_range": "高光范围"
        },
        "outputs": {
            "image": "图像"
        }
    },
    "LayerColor: YUV": {
        "title": "RGB",
        "inputs": {
            "image": "图像"
        },
        "widgets": {
            "Y": "Y",
            "U": "U",
            "V": "V"
        },
        "outputs": {
            "image": "图像"
        }
    },


    "LayerUtility: ColorImage": {
        "title": "纯色图像",
        "widgets": {
            "width": "宽度",
            "height": "高度",
            "color": "颜色"
        },
        "outputs": {
            "image": "图像"
        }
    },
    "LayerUtility: ColorImage V2": {
        "title": "纯色图像_V2",
        "inputs": {
            "size_as": "参考大小"
        },
        "widgets": {
            "size": "大小",
            "custom_width": "自定义宽度",
            "custom_height": "自定义高度",
            "color": "颜色"
        },
        "outputs": {
            "image": "图像"
        }
    },
    "LayerUtility: ColorPicker": {
        "title": "取色器",
        "widgets": {
            "color": "颜色",
            "mode": "模式"
        },
        "outputs": {
            "value": "值"
        }
    },
    "LayerUtility: CropBoxResolve": {
        "title": "裁剪框分析",
        "inputs": {
            "crop_box": "裁剪框"
        },
        "outputs": {
            "x": "X",
            "y": "Y",
            "width": "宽度",
            "height": "高度"
        }
    },
    "LayerUtility: CropByMask": {
        "title": "遮罩裁剪",
        "inputs": {
            "image": "图像",
            "mask_for_crop": "遮罩"
        },
        "widgets": {
            "invert_mask": "反转遮罩",
            "detect": "检测方法",
            "top_reserve": "顶端保留",
            "bottom_reserve": "底部保留",
            "left_reserve": "左侧保留",
            "right_reserve": "右侧保留"
        },
        "outputs": {
            "croped_image": "裁剪图像",
            "croped_mask": "裁剪遮罩",
            "crop_box": "裁剪框",
            "box_preview": "裁剪框预览"
        }
    },
    "LayerUtility: CropByMask V2": {
        "title": "遮罩裁剪_V2",
        "inputs": {
            "image": "图像",
            "mask_for_crop": "遮罩",
            "crop_box": "裁剪框"
        },
        "widgets": {
            "invert_mask": "反转遮罩",
            "detect": "检测方法",
            "top_reserve": "顶端保留",
            "bottom_reserve": "底部保留",
            "left_reserve": "左侧保留",
            "right_reserve": "右侧保留"
        },
        "outputs": {
            "croped_image": "裁剪图像",
            "croped_mask": "裁剪遮罩",
            "crop_box": "裁剪框",
            "box_preview": "裁剪框预览"
        }
    },
    "LayerUtility: ExtendCanvas": {
        "title": "扩展画布",
        "inputs": {
            "image": "图像",
            "color": "颜色",
            "mask": "遮罩"
        },
        "widgets": {
            "invert_mask": "反转遮罩",
            "top": "上",
            "bottom": "下",
            "left": "左",
            "right": "右"
        },
        "outputs": {
            "image": "图像",
            "mask": "遮罩"
        }
    },
    "LayerUtility: GetColorTone": {
        "title": "获取色调",
        "inputs": {
            "image": "图像"
        },
        "widgets": {
            "mode": "模式"
        },
        "outputs": {
            "RGB color in HEX": "HEX字符串",
            "HSV color in list": "HSV色值列表"
        }
    },
    "LayerUtility: GetColorToneV2": {
        "title": "获取色调_V2",
        "inputs": {
            "image": "图像",
            "mask": "遮罩"
        },
        "widgets": {
            "mode": "模式",
            "color_of": "目标颜色",
            "remove_bkgd_method": "移除背景方法",
            "invert_mask": "反转遮罩",
            "mask_grow": "遮罩扩张"
        },
        "outputs": {
            "image": "图像",
            "color_in_hex": "HEX字符串",
            "HSV color in list": "HSV色值列表"
        }
    },
    "LayerUtility: GetImageSize": {
        "title": "获取图像尺寸",
        "inputs": {
            "image": "图像"
        },
        "outputs": {
            "width": "宽度",
            "height": "高度",
            "original_size": "原始大小"
        }
    },
    "LayerUtility: GradientImage": {
        "title": "渐变图像",
        "widgets": {
            "width": "宽度",
            "height": "高度",
            "angle": "角度",
            "start_color": "起始色",
            "end_color": "结束色"
        },
        "outputs": {
            "image": "图像"
        }
    },
    "LayerUtility: GradientImage V2": {
        "title": "渐变图像_V2",
        "inputs": {
            "size_as": "参考大小"
        },
        "widgets": {
            "size": "大小",
            "custom_width": "自定义宽度",
            "custom_height": "自定义高度",
            "angle": "角度",
            "start_color": "起始色",
            "end_color": "结束色"
        },
        "outputs": {
            "image": "图像"
        }
    },
    "LayerUtility: ImageAutoCrop": {
        "title": "图像自动裁剪",
        "inputs": {
            "image": "图像"
        },
        "widgets": {
            "background_color": "背景颜色",
            "aspect_ratio": "宽高比",
            "proportional_height": "比例高",
            "proportional_width": "比例宽",
            "scale_to_longest_side": "按长边缩放",
            "longest_side": "长边长度",
            "detect": "检测方法",
            "border_reserve": "保留边框",
            "ultra_detail_range": "细化边缘",
            "matting_method": "遮罩生成方法",
            "sam_model": "SAM模型",
            "grounding_dino_model": "GroundingDINO模型",
            "sam_threshold": "SAM阈值",
            "sam_prompt": "SAM提示词"
        },
        "outputs": {
            "cropped_image": "裁剪图像",
            "box_preview": "裁剪框预览",
            "cropped_mask": "裁剪遮罩"
        }
    },
    "LayerUtility: ImageAutoCrop V2": {
        "title": "图像自动裁剪",
        "inputs": {
            "image": "图像",
            "mask": "遮罩"
        },
        "widgets": {
            "fill_background": "填充背景",
            "background_color": "背景颜色",
            "aspect_ratio": "宽高比",
            "proportional_height": "比例高",
            "proportional_width": "比例宽",
            "scale_to_longest_side": "按长边缩放",
            "longest_side": "长边长度",
            "detect": "检测方法",
            "border_reserve": "保留边框",
            "ultra_detail_range": "细化边缘",
            "matting_method": "遮罩生成方法",
            "sam_model": "SAM模型",
            "grounding_dino_model": "GroundingDINO模型",
            "sam_threshold": "SAM阈值",
            "sam_prompt": "SAM提示词"
        },
        "outputs": {
            "cropped_image": "裁剪图像",
            "box_preview": "裁剪框预览",
            "cropped_mask": "裁剪遮罩"
        }
    },
    "LayerUtility: ImageBlend": {
        "title": "混合",
        "inputs": {
            "background_image": "背景图像",
            "layer_mask": "遮罩层",
            "layer_image": "图像层"
        },
        "widgets": {
            "invert_mask": "反转遮罩",
            "blend_mode": "混合模式",
            "opacity": "不透明"
        },
        "outputs": {
            "image": "图像"
        }
    },
    "LayerUtility: ImageBlendAdvance": {
        "title": "混合(高级)",
        "inputs": {
            "background_image": "背景图像",
            "layer_mask": "遮罩层",
            "layer_image": "图像层"
        },
        "widgets": {
            "invert_mask": "反转遮罩",
            "blend_mode": "混合模式",
            "opacity": "不透明",
            "x_percent": "X百分比",
            "y_percent": "Y百分比",
            "mirror": "镜像",
            "scale": "缩放",
            "aspect_ratio": "宽高比",
            "rotate": "旋转",
            "transform_method": "采样方法",
            "anti_aliasing": "抗锯齿"
        },
        "outputs": {
            "image": "图像",
            "mask": "遮罩"
        }
    },
    "LayerUtility: ImageChannelMerge": {
        "title": "通道合并",
        "inputs": {
            "channel_1": "通道_1",
            "channel_2": "通道_2",
            "channel_3": "通道_3",
            "channel_4": "通道_4"
        },
        "widgets": {
            "mode": "模式"
        },
        "outputs": {
            "image": "图像"
        }
    },
    "LayerUtility: ImageChannelSplit": {
        "title": "通道拆分",
        "inputs": {
            "image": "图像"
        },
        "widgets": {
            "mode": "模式"
        },
        "outputs": {
            "channel_1": "通道_1",
            "channel_2": "通道_2",
            "channel_3": "通道_3",
            "channel_4": "通道_4"
        }
    },
    "LayerUtility: ImageCombineAlpha": {
        "title": "图像合并Alpha",
        "inputs": {
            "RGB_image": "RGB图像",
            "mask": "遮罩"
        },
        "outputs": {
            "RGBA_image": "RGBA图像"
        }
    },
    "LayerUtility: ImageMaskScaleAs": {
        "title": "参考缩放",
        "inputs": {
            "image": "图像",
            "mask": "遮罩"
        },
        "widgets": {
            "scale_as": "参考大小",
            "fit": "裁剪模式",
            "method": "采样方法"
        },
        "outputs": {
            "image": "图像",
            "mask": "遮罩",
            "original_size": "原始大小"
        }
    },
    "LayerUtility: ImageOpacity": {
        "title": "不透明",
        "inputs": {
            "image": "图像",
            "mask": "遮罩"
        },
        "widgets": {
            "opacity": "不透明",
            "invert_mask": "反转遮罩"
        },
        "outputs": {
            "image": "图像",
            "mask": "遮罩"
        }
    },
    "LayerUtility: ImageRemoveAlpha": {
        "title": "移除Alpha",
        "inputs": {
            "RGBA_image": "RGBA图像"
        },
        "widgets": {
            "fill_background": "填充背景",
            "background_color": "背景颜色"
        },
        "outputs": {
            "RGB_image": "RGB图像"
        }
    },
    "LayerUtility: ImageRewardFilter": {
        "title": "图像美学过滤",
        "inputs": {
            "images": "图像"
        },
        "widgets": {
            "prompt": "提示词",
            "output_num": "输出数量"
        },
        "outputs": {
            "images": "图像",
            "obsolete_images": "过滤图像"
        }
    },
    "LayerUtility: ImageScaleByAspectRatio": {
        "title": "按宽高比缩放",
        "inputs": {
            "image": "图像",
            "mask": "遮罩"
        },
        "widgets": {
            "aspect_ratio": "宽高比",
            "proportional_width": "比例宽",
            "proportional_height": "比例高",
            "fit": "缩放模式",
            "method": "采样方法",
            "round_to_multiple": "倍数取整",
            "scale_to_longest_side": "按长边缩放",
            "longest_side": "长边长度"
        },
        "outputs": {
            "image": "图像",
            "mask": "遮罩",
            "original_size": "原始大小"
        }
    },
    "LayerUtility: ImageScaleByAspectRatio V2": {
        "title": "按宽高比缩放_V2",
        "inputs": {
            "image": "图像",
            "mask": "遮罩"
        },
        "widgets": {
            "aspect_ratio": "宽高比",
            "proportional_width": "比例宽",
            "proportional_height": "比例高",
            "fit": "缩放模式",
            "method": "采样方法",
            "round_to_multiple": "倍数取整",
            "scale_to_side": "缩放到边",
            "scale_to_length": "缩放到长度"
        },
        "outputs": {
            "image": "图像",
            "mask": "遮罩",
            "original_size": "原始大小"
        }
    },
    "LayerUtility: ImageScaleRestore": {
        "title": "缩放恢复",
        "inputs": {
            "image": "图像",
            "mask": "遮罩",
            "original_size": "原始大小"
        },
        "widgets": {
            "scale": "缩放",
            "method": "采样方法",
            "scale_to_longest_side": "按长边缩放",
            "longest_side": "长边长度"
        },
        "outputs": {
            "image": "图像",
            "mask": "遮罩",
            "original_size": "原始大小"
        }
    },
    "LayerUtility: ImageScaleRestore V2": {
        "title": "缩放恢复_V2",
        "inputs": {
            "image": "图像",
            "mask": "遮罩",
            "original_size": "原始大小"
        },
        "widgets": {
            "scale": "缩放",
            "method": "采样方法",
            "scale_by": "缩放方法",
            "scale_by_length": "缩放长度"
        },
        "outputs": {
            "image": "图像",
            "mask": "遮罩",
            "original_size": "原始大小"
        }
    },
    "LayerUtility: ImageShift": {
        "title": "位移",
        "inputs": {
            "image": "图像",
            "mask": "遮罩"
        },
        "widgets": {
            "shift_x": "X",
            "shift_y": "Y",
            "cyclic": "循环",
            "background_color": "背景颜色",
            "border_mask_width": "接缝宽度",
            "border_mask_blur": "接缝模糊"
        },
        "outputs": {
            "image": "图像",
            "mask": "遮罩",
            "border_mask": "接缝遮罩"
        }
    },
    "LayerUtility: LaMa": {
        "title": "LaMa",
        "inputs": {
            "image": "图像",
            "mask": "遮罩"
        },
        "widgets": {
            "lama_model": "LaMa模型",
            "device": "设备",
            "invert_mask": "反转遮罩",
            "mask_grow": "遮罩扩张",
            "mask_blur": "遮罩模糊"
        },
        "outputs": {
            "image": "图像"
        }
    },
    "LayerUtility: LayerImageTransform": {
        "title": "图像变换",
        "inputs": {
            "image": "图像"
        },
        "widgets": {
            "x": "X",
            "y": "Y",
            "mirror": "镜像",
            "scale": "缩放",
            "aspect_ratio": "宽高比",
            "rotate": "旋转",
            "transform_method": "采样方法",
            "anti_aliasing": "抗锯齿"
        },
        "outputs": {
            "image": "图像"
        }
    },
    "LayerUtility: LayerMaskTransform": {
        "title": "图像变换",
        "inputs": {
            "mask": "遮罩"
        },
        "widgets": {
            "x": "X",
            "y": "Y",
            "mirror": "镜像",
            "scale": "缩放",
            "aspect_ratio": "宽高比",
            "rotate": "旋转",
            "transform_method": "采样方法",
            "anti_aliasing": "抗锯齿"
        },
        "outputs": {
            "mask": "遮罩"
        }
    },
    "LayerUtility: PrintInfo": {
        "title": "输出到控制台",
        "inputs": {
            "anything": "任意"
        }
    },
    "LayerUtility: PromptEmbellish": {
        "title": "提示词润色",
        "inputs": {
            "image": "图像"
        },
        "widgets": {
            "api": "API",
            "token_limit": "Token限制",
            "describe": "描述"
        },
        "outputs": {
            "text": "文本"
        }
    },
    "LayerUtility: PromptTagger": {
        "title": "提示词反推",
        "inputs": {
            "image": "图像"
        },
        "widgets": {
            "api": "API",
            "token_limit": "Token限制",
            "exclude_word": "排除词",
            "replace_with_word": "替换词"
        },
        "outputs": {
            "text": "文本"
        }
    },
    "LayerUtility: RestoreCropBox": {
        "title": "裁剪恢复",
        "inputs": {
            "background_image": "背景图像",
            "cropped_image": "裁剪图像",
            "cropped_mask": "裁剪遮罩",
            "crop_box": "裁剪框"
        },
        "widgets": {
            "invert_mask": "反转遮罩"
        },
        "outputs": {
            "image": "图像",
            "mask": "遮罩"
        }
    },
    "LayerUtility: SimpleTextImage": {
        "title": "文本图像(简易)",
        "inputs": {
            "size_as": "参考大小"
        },
        "widgets": {
            "text": "文本",
            "font_file": "字体",
            "align": "对齐到",
            "char_per_line": "每行字数",
            "leading": "行间距",
            "font_size": "字体大小",
            "text_color": "文本颜色",
            "x_offset": "X偏移",
            "y_offset": "Y偏移",
            "width": "宽度",
            "height": "高度"
        },
        "outputs": {
            "image": "图像",
            "mask": "遮罩"
        }
    },
    "LayerUtility: TextImage": {
        "title": "文本图像",
        "inputs": {
            "size_as": "参考大小"
        },
        "widgets": {
            "text": "文本",
            "font_file": "字体",
            "spacing": "字间距",
            "leading": "行间距",
            "horizontal_border": "侧边边距",
            "vertical_border": "顶部边距",
            "scale": "缩放",
            "variation_range": "字符变化范围",
            "variation_seed": "字符变化种子",
            "layout": "排版",
            "width": "宽度",
            "height": "高度",
            "text_color": "文本颜色",
            "background_color": "背景颜色"
        },
        "outputs": {
            "image": "图像",
            "mask": "遮罩"
        }
    },
    "LayerUtility: TextJoin": {
        "title": "文本合并",
        "widgets": {
            "text_1": "文本_1",
            "text_2": "文本_2",
            "text_3": "文本_3",
            "text_4": "文本_4"
        },
        "outputs": {
            "text": "文本"
        }
    },
    "LayerUtility: XY to Percent": {
        "title": "XY坐标到百分比坐标",
        "widgets": {
            "background_image": "背景图像",
            "layer_image": "图像层",
            "x": "X",
            "y": "Y"
        },
        "outputs": {
            "x_percent": "X百分比",
            "y_percent": "Y百分比"
        }
    },


    "LayerStyle: ColorOverlay": {
        "title": "颜色覆盖",
        "inputs": {
            "background_image": "背景图像",
            "layer_image": "图像层",
            "layer_mask": "遮罩层"
        },
        "widgets": {
            "invert_mask": "反转遮罩",
            "blend_mode": "混合模式",
            "opacity": "不透明",
            "color": "颜色"
        },
        "outputs": {
            "image": "图像"
        }
    },
    "LayerStyle: DropShadow": {
        "title": "生成阴影",
        "inputs": {
            "background_image": "背景图像",
            "layer_image": "图像层",
            "layer_mask": "遮罩层"
        },
        "widgets": {
            "invert_mask": "反转遮罩",
            "blend_mode": "混合模式",
            "opacity": "不透明",
            "distance_x": "X距离",
            "distance_y": "Y距离",
            "grow": "扩张",
            "blur": "模糊",
            "shadow_color": "阴影色"
        },
        "outputs": {
            "image": "图像"
        }
    },
    "LayerStyle: Gradient Map": {
        "title": "渐变映射",
        "inputs": {
            "image": "图像",
            "layer_mask": "遮罩层"
        },
        "widgets": {
            "start_color": "起始色",
            "mid_color": "中间色",
            "end_color": "结束色",
            "mid_point": "中间点",
            "opacity": "不透明"
        },
        "outputs": {
            "image": "图像",
            "gradient": "渐变"
        }
    },
    "LayerStyle: GradientOverlay": {
        "title": "渐变覆盖",
        "inputs": {
            "background_image": "背景图像",
            "layer_image": "图像层",
            "layer_mask": "遮罩层"
        },
        "widgets": {
            "invert_mask": "反转遮罩",
            "blend_mode": "混合模式",
            "opacity": "不透明",
            "start_color": "起始色",
            "start_alpha": "起始透明",
            "end_color": "结束色",
            "end_alpha": "结束透明",
            "angle": "角度"
        },
        "outputs": {
            "image": "图像"
        }
    },
    "LayerStyle: InnerGlow": {
        "title": "内发光",
        "inputs": {
            "background_image": "背景图像",
            "layer_image": "图像层",
            "layer_mask": "遮罩层"
        },
        "widgets": {
            "invert_mask": "反转遮罩",
            "blend_mode": "混合模式",
            "opacity": "不透明",
            "brightness": "亮度",
            "glow_range": "范围",
            "blur": "模糊",
            "light_color": "发光色",
            "glow_color": "辉光色"
        },
        "outputs": {
            "image": "图像"
        }
    },
    "LayerStyle: InnerShadow": {
        "title": "内阴影",
        "inputs": {
            "background_image": "背景图像",
            "layer_image": "图像层",
            "layer_mask": "遮罩层"
        },
        "widgets": {
            "invert_mask": "反转遮罩",
            "blend_mode": "混合模式",
            "opacity": "不透明",
            "distance_x": "X距离",
            "distance_y": "Y距离",
            "grow": "扩张",
            "blur": "模糊",
            "shadow_color": "阴影色"
        },
        "outputs": {
            "image": "图像"
        }
    },
    "LayerStyle: OuterGlow": {
        "title": "外发光",
        "inputs": {
            "background_image": "背景图像",
            "layer_image": "图像层",
            "layer_mask": "遮罩层"
        },
        "widgets": {
            "invert_mask": "反转遮罩",
            "blend_mode": "混合模式",
            "opacity": "不透明",
            "brightness": "亮度",
            "glow_range": "范围",
            "blur": "模糊",
            "light_color": "发光色",
            "glow_color": "辉光色"
        },
        "outputs": {
            "image": "图像"
        }
    },
    "LayerStyle: Stroke": {
        "title": "描边",
        "inputs": {
            "background_image": "背景图像",
            "layer_image": "图像层",
            "layer_mask": "遮罩层"
        },
        "widgets": {
            "invert_mask": "反转遮罩",
            "blend_mode": "混合模式",
            "opacity": "不透明",
            "stroke_grow": "扩张",
            "stroke_width": "宽度",
            "blur": "模糊",
            "stroke_color": "描边色"
        },
        "outputs": {
            "image": "图像"
        }
    },
    "LayerStyle: ColorOverlay V2": {
        "title": "颜色覆盖 V2",
        "inputs": {
            "background_image": "背景图像",
            "layer_image": "图像层",
            "layer_mask": "遮罩层"
        },
        "widgets": {
            "invert_mask": "反转遮罩",
            "blend_mode": "混合模式",
            "opacity": "不透明",
            "color": "颜色"
        },
        "outputs": {
            "image": "图像"
        }
    },
    "LayerStyle: DropShadow V2": {
        "title": "生成阴影 V2",
        "inputs": {
            "background_image": "背景图像",
            "layer_image": "图像层",
            "layer_mask": "遮罩层"
        },
        "widgets": {
            "invert_mask": "反转遮罩",
            "blend_mode": "混合模式",
            "opacity": "不透明",
            "distance_x": "X距离",
            "distance_y": "Y距离",
            "grow": "扩张",
            "blur": "模糊",
            "shadow_color": "阴影色"
        },
        "outputs": {
            "image": "图像"
        }
    },
    "LayerStyle: GradientOverlay V2": {
        "title": "渐变覆盖 V2",
        "inputs": {
            "background_image": "背景图像",
            "layer_image": "图像层",
            "layer_mask": "遮罩层"
        },
        "widgets": {
            "invert_mask": "反转遮罩",
            "blend_mode": "混合模式",
            "opacity": "不透明",
            "start_color": "起始色",
            "start_alpha": "起始透明",
            "end_color": "结束色",
            "end_alpha": "结束透明",
            "angle": "角度"
        },
        "outputs": {
            "image": "图像"
        }
    },
    "LayerStyle: InnerGlow V2": {
        "title": "内发光 V2",
        "inputs": {
            "background_image": "背景图像",
            "layer_image": "图像层",
            "layer_mask": "遮罩层"
        },
        "widgets": {
            "invert_mask": "反转遮罩",
            "blend_mode": "混合模式",
            "opacity": "不透明",
            "brightness": "亮度",
            "glow_range": "范围",
            "blur": "模糊",
            "light_color": "发光色",
            "glow_color": "辉光色"
        },
        "outputs": {
            "image": "图像"
        }
    },
    "LayerStyle: InnerShadow V2": {
        "title": "内阴影 V2",
        "inputs": {
            "background_image": "背景图像",
            "layer_image": "图像层",
            "layer_mask": "遮罩层"
        },
        "widgets": {
            "invert_mask": "反转遮罩",
            "blend_mode": "混合模式",
            "opacity": "不透明",
            "distance_x": "X距离",
            "distance_y": "Y距离",
            "grow": "扩张",
            "blur": "模糊",
            "shadow_color": "阴影色"
        },
        "outputs": {
            "image": "图像"
        }
    },
    "LayerStyle: OuterGlow V2": {
        "title": "外发光 V2",
        "inputs": {
            "background_image": "背景图像",
            "layer_image": "图像层",
            "layer_mask": "遮罩层"
        },
        "widgets": {
            "invert_mask": "反转遮罩",
            "blend_mode": "混合模式",
            "opacity": "不透明",
            "brightness": "亮度",
            "glow_range": "范围",
            "blur": "模糊",
            "light_color": "发光色",
            "glow_color": "辉光色"
        },
        "outputs": {
            "image": "图像"
        }
    },
    "LayerStyle: Stroke V2": {
        "title": "描边 V2",
        "inputs": {
            "background_image": "背景图像",
            "layer_image": "图像层",
            "layer_mask": "遮罩层"
        },
        "widgets": {
            "invert_mask": "反转遮罩",
            "blend_mode": "混合模式",
            "opacity": "不透明",
            "stroke_grow": "扩张",
            "stroke_width": "宽度",
            "blur": "模糊",
            "stroke_color": "描边色"
        },
        "outputs": {
            "image": "图像"
        }
    },


    "LayerMask: BiRefNetUltra": {
        "title": "BiRefNet Ultra",
        "inputs": {
            "image": "图像"
        },
        "widgets": {
            "detail_method": "细节处理方法",
            "detail_erode": "细节消融",
            "detail_dilate": "细节膨胀",
            "black_point": "黑色阈值",
            "white_point": "白色阈值",
            "process_detail": "处理细节",
            "device": "设备",
            "max_megapixels": "Vitmatte最大尺寸"
        },
        "outputs": {
            "image": "图像",
            "mask": "遮罩"
        }
    },
    "LayerMask: BiRefNetUltraV2": {
        "title": "BiRefNet Ultra V2",
        "inputs": {
            "image": "图像",
            "birefnet_model": "BiRefNet模型"
        },
        "widgets": {
            "detail_method": "细节处理方法",
            "detail_erode": "细节消融",
            "detail_dilate": "细节膨胀",
            "black_point": "黑色阈值",
            "white_point": "白色阈值",
            "process_detail": "处理细节",
            "device": "设备",
            "max_megapixels": "Vitmatte最大尺寸"
        },
        "outputs": {
            "image": "图像",
            "mask": "遮罩"
        }
    },
    "LayerMask: BlendIf Mask": {
        "title": "混合颜色带",
        "inputs": {
            "image": "图像",
            "mask": "遮罩"
        },
        "widgets": {
            "invert_mask": "反转遮罩",
            "blend_if": "颜色带",
            "black_point": "黑色阈值",
            "black_range": "黑色范围",
            "white_point": "白色阈值",
            "white_range": "白色范围"
        },
        "outputs": {
            "mask": "遮罩"
        }
    },
    "LayerMask: CreateGradientMask": {
        "title": "生成渐变遮罩",
        "inputs": {
            "size_as": "参考大小"
        },
        "widgets": {
            "width": "宽度",
            "height": "高度",
            "gradient_side": "方向",
            "gradient_scale": "缩放",
            "gradient_offset": "偏移",
            "opacity": "不透明"
        },
        "outputs": {
            "mask": "遮罩"
        }
    },
    "LayerMask: EVFSAMUltra": {
        "title": "EVSAM Ultra",
        "inputs": {
            "image": "图像"
        },
        "widgets": {
            "model": "模型",
            "precision": "精度",
            "load_in_bit": "加载位精度",
            "prompt": "提示词",
            "detail_method": "细节处理方法",
            "detail_erode": "细节消融",
            "detail_dilate": "细节膨胀",
            "black_point": "黑色阈值",
            "white_point": "白色阈值",
            "process_detail": "处理细节",
            "device": "设备",
            "max_megapixels": "Vitmatte最大尺寸"
        }
    },
    "LayerMask: Florence2Ultra": {
        "title": "Florence2 Ultra",
        "inputs": {
            "florence2_model": "Florence2模型",
            "image": "图像"
        },
        "widgets": {
            "task": "任务",
            "text_input": "文本",
            "detail_method": "细节处理方法",
            "detail_erode": "细节消融",
            "detail_dilate": "细节膨胀",
            "black_point": "黑色阈值",
            "white_point": "白色阈值",
            "process_detail": "处理细节",
            "device": "设备",
            "max_megapixels": "Vitmatte最大尺寸"
        },
        "outputs": {
            "image": "图像",
            "mask": "遮罩"
        }
    },
    "LayerMask: ImageToMask": {
        "title": "图像到遮罩",
        "inputs": {
            "image": "图像",
            "mask": "遮罩"
        },
        "widgets": {
            "channel": "通道",
            "black_point": "黑色阈值",
            "white_point": "白色阈值",
            "gray_point": "灰色阈值",
            "invert_output_mask": "反转遮罩输出"
        },
        "outputs": {
            "mask": "遮罩"
        }
    },
    "LayerMask: MaskBoxDetect": {
        "title": "检测遮罩区域",
        "inputs": {
            "mask": "遮罩"
        },
        "widgets": {
            "detect": "检测方法",
            "x_adjust": "X偏移",
            "y_adjust": "Y偏移",
            "scale_adjust": "缩放"
        },
        "outputs": {
            "box_preview": "图像",
            "x_percent": "X百分比",
            "y_percent": "Y百分比",
            "width": "宽度",
            "height": "高度",
            "x": "X",
            "y": "Y"
        }
    },
    "LayerMask: MaskByColor": {
        "title": "颜色到遮罩",
        "inputs": {
            "image": "图像",
            "mask": "遮罩"
        },
        "widgets": {
            "color": "颜色",
            "color_in_HEX": "HEX颜色",
            "threshold": "阈值",
            "fix_gap": "填缝",
            "fix_threshold": "修补阈值",
            "invert_mask": "反转遮罩"
        },
        "outputs": {
            "mask": "遮罩"
        }
    },
    "LayerMask: MaskByDifferent": {
        "title": "差值遮罩",
        "inputs": {
            "image_1": "图像_1",
            "image_2": "图像_2"
        },
        "widgets": {
            "gain": "增强",
            "fix_gap": "填缝",
            "fix_threshold": "修补阈值",
            "main_subject_detect": "仅检测主体"
        },
        "outputs": {
            "mask": "遮罩"
        }
    },
    "LayerMask: MaskEdgeShrink": {
        "title": "遮罩边缘收缩",
        "inputs": {
            "mask": "遮罩"
        },
        "widgets": {
            "invert_mask": "反转遮罩",
            "shrink_level": "等级",
            "soft": "柔化",
            "edge_shrink": "幅度",
            "edge_reserve": "保留细节"
        },
        "outputs": {
            "mask": "遮罩"
        }
    },
    "LayerMask: MaskEdgeUltraDetail": {
        "title": "遮罩细化",
        "inputs": {
            "image": "图像",
            "mask": "遮罩"
        },
        "widgets": {
            "method": "方法",
            "mask_grow": "遮罩扩张",
            "fix_gap": "填缝",
            "fix_threshold": "修补阈值",
            "detail_range": "细节范围",
            "black_point": "黑色阈值",
            "white_point": "白色阈值"
        },
        "outputs": {
            "image": "图像",
            "mask": "遮罩"
        }
    },
    "LayerMask: MaskEdgeUltraDetail V2": {
        "title": "遮罩细化 V2",
        "inputs": {
            "image": "图像",
            "mask": "遮罩"
        },
        "widgets": {
            "method": "方法",
            "mask_grow": "遮罩扩张",
            "fix_gap": "填缝",
            "fix_threshold": "修补阈值",
            "edge_erode": "边缘消融",
            "edge_dilate": "边缘膨胀",
            "edte_dilate": "边缘膨胀",
            "black_point": "黑色阈值",
            "white_point": "白色阈值"
        },
        "outputs": {
            "image": "图像",
            "mask": "遮罩"
        }
    },
    "LayerMask: MaskGradient": {
        "title": "遮罩渐变",
        "inputs": {
            "mask": "遮罩"
        },
        "widgets": {
            "invert_mask": "反转遮罩",
            "gradient_side": "方向",
            "gradient_scale": "缩放",
            "gradient_offset": "偏移",
            "opacity": "不透明"
        },
        "outputs": {
            "mask": "遮罩"
        }
    },
    "LayerMask: MaskGrain": {
        "title": "遮罩颗粒",
        "inputs": {
            "mask": "遮罩"
        },
        "widgets": {
            "grain": "颗粒",
            "invert_mask": "反转遮罩"
        },
        "outputs": {
            "mask": "遮罩"
        }
    },
    "LayerMask: MaskGrow": {
        "title": "遮罩扩张",
        "inputs": {
            "mask": "遮罩"
        },
        "widgets": {
            "invert_mask": "反转遮罩",
            "grow": "扩张",
            "blur": "模糊"
        },
        "outputs": {
            "mask": "遮罩"
        }
    },
    "LayerMask: MaskInvert": {
        "title": "遮罩反转",
        "inputs": {
            "mask": "遮罩"
        },
        "widgets": {
            "invert_mask": "反转遮罩",
            "blur": "模糊",
            "angle": "角度"
        },
        "outputs": {
            "mask": "遮罩"
        }
    },
    "LayerMask: MaskMotionBlur": {
        "title": "遮罩动态模糊",
        "inputs": {
            "mask": "遮罩"
        },
        "widgets": {
            "invert_mask": "反转遮罩",
            "blur": "模糊",
            "angle": "角度"
        },
        "outputs": {
            "mask": "遮罩"
        }
    },
    "LayerMask: MaskPreview": {
        "title": "遮罩预览",
        "inputs": {
            "mask": "遮罩"
        }
    },
    "LayerMask: MaskStroke": {
        "title": "遮罩描边",
        "inputs": {
            "mask": "遮罩"
        },
        "widgets": {
            "invert_mask": "反转遮罩",
            "stroke_grow": "扩张",
            "stroke_width": "宽度",
            "blur": "模糊"
        }
    },
    "LayerMask: MediapipeFacialSegment": {
        "title": "Mediapipe面部分割",
        "inputs": {
            "image": "图像"
        },
        "widgets": {
            "left_eye": "左眼",
            "left_eyebrow": "左眉",
            "right_eye": "右眼",
            "right_eyebrow": "右眉",
            "lips": "嘴唇",
            "tooth": "牙齿"
        },
        "outputs": {
            "image": "图像",
            "mask": "遮罩"
        }
    },
    "LayerMask: BBoxJoin": {
        "title": "合并BBox",
        "inputs": {
            "bboxes_1": "BBoxes_1",
            "bboxes_2": "BBoxes_2",
            "bboxes_3": "BBoxes_3",
            "bboxes_4": "BBoxes_4"
        },
        "outputs": {
            "bboxes": "BBoxes"
        }
    },
    "LayerMask: ObjectDetectorFL2": {
        "title": "物体检测（Florence2）",
        "inputs": {
            "image": "图像",
            "florence2_model": "Florence2模型"
        },
        "widgets": {
            "prompt": "提示词",
            "sort_method": "排序方法",
            "bbox_select": "选择BBox",
            "select_index": "选择编号"
        },
        "outputs": {
            "bboxes": "BBoxes",
            "preview": "预览图像"
        }
    },
    "LayerMask: ObjectDetectorMask": {
        "title": "物体检测（遮罩）",
        "inputs": {
            "object_mask": "物体遮罩"
        },
        "widgets": {
            "sort_method": "排序方法",
            "bbox_select": "选择BBox",
            "select_index": "选择编号"
        },
        "outputs": {
            "bboxes": "BBoxes",
            "preview": "预览图像"
        }
    },
    "LayerMask: ObjectDetectorYOLO8": {
        "title": "物体检测（Yolov8）",
        "inputs": {
            "image": "图像"
        },
        "widgets": {
            "yolo_model": "Yolo模型",
            "sort_method": "排序方法",
            "bbox_select": "选择BBox",
            "select_index": "选择编号"
        },
        "outputs": {
            "bboxes": "BBoxes",
            "preview": "预览图像"
        }
    },
    "LayerMask: ObjectDetectorYOLOWorld": {
        "title": "物体检测（YoloWorld）",
        "inputs": {
            "image": "图像"
        },
        "widgets": {
            "yolo_world_model": "YoloWorld模型",
            "confidence_threshold": "置信度",
            "nms_iou_threshold": "非极大值抑制阈值",
            "prompt": "提示词",
            "sort_method": "排序方法",
            "bbox_select": "选择BBox",
            "select_index": "选择编号"
        },
        "outputs": {
            "bboxes": "BBoxes",
            "preview": "预览图像"
        }
    },
    "LayerMask: PersonMaskUltra": {
        "title": "人像遮罩 Ultra",
        "inputs": {
            "images": "图像"
        },
        "widgets": {
            "face": "面部",
            "hair": "头发",
            "body": "身体",
            "clothes": "衣服",
            "accessories": "饰品",
            "background": "背景",
            "confidence": "置信度",
            "detail_range": "细节范围",
            "black_point": "黑色阈值",
            "white_point": "白色阈值",
            "process_detail": "处理细节"
        },
        "outputs": {
            "image": "图像",
            "mask": "遮罩"
        }
    },
    "LayerMask: PersonMaskUltra V2": {
        "title": "人像遮罩 Ultra V2",
        "inputs": {
            "images": "图像"
        },
        "widgets": {
            "face": "面部",
            "hair": "头发",
            "body": "身体",
            "clothes": "衣服",
            "accessories": "饰品",
            "background": "背景",
            "confidence": "置信度",
            "detail_method": "细节处理方法",
            "detail_erode": "细节消融",
            "detail_dilate": "细节膨胀",
            "black_point": "黑色阈值",
            "white_point": "白色阈值",
            "process_detail": "处理细节"
        },
        "outputs": {
            "image": "图像",
            "mask": "遮罩"
        }
    },
    "LayerMask: PixelSpread": {
        "title": "像素扩张",
        "inputs": {
            "image": "图像",
            "mask": "遮罩"
        },
        "widgets": {
            "invert_mask": "反转遮罩",
            "mask_grow": "遮罩扩张"
        },
        "outputs": {
            "image": "图像"
        }
    },
    "LayerMask: RemBgUltra": {
        "title": "移除背景",
        "inputs": {
            "image": "图像"
        },
        "widgets": {
            "detail_range": "细节范围",
            "black_point": "黑色阈值",
            "white_point": "白色阈值",
            "process_detail": "处理细节"
        },
        "outputs": {
            "image": "图像",
            "mask": "遮罩"
        }
    },
    "LayerMask: RmBgUltra V2": {
        "title": "移除背景 V2",
        "inputs": {
            "image": "图像"
        },
        "widgets": {
            "detail_method": "细节处理方法",
            "detail_erode": "细节消融",
            "detail_dilate": "细节膨胀",
            "black_point": "黑色阈值",
            "white_point": "白色阈值",
            "process_detail": "处理细节"
        },
        "outputs": {
            "image": "图像",
            "mask": "遮罩"
        }
    },
    "LayerMask: SAM2Ultra": {
        "title": "SAM2 Ultra",
        "inputs": {
            "image": "图像",
            "bboxes": "BBoxes"
        },
        "widgets": {
            "sam2_model": "SAM2模型",
            "precision": "精度",
            "bbox_select": "选择BBox",
            "select_index": "选择编号",
            "cache_model": "缓存模型",
            "detail_method": "细节处理方法",
            "detail_erode": "细节消融",
            "detail_dilate": "细节膨胀",
            "black_point": "黑色阈值",
            "white_point": "白色阈值",
            "process_detail": "处理细节",
            "device": "设备",
            "max_megapixels": "Vitmatte最大尺寸"
        },
        "outputs": {
            "image": "图像",
            "mask": "遮罩"
        }
    },
    "LayerMask: SAM2VideoUltra": {
        "title": "SAM2视频 Ultra",
        "inputs": {
            "image": "图像",
            "bboxes": "BBoxes",
            "first_frame_mask": "首帧遮罩",
            "pre_masK": "关注层遮罩"
        },
        "widgets": {
            "sam2_model": "SAM2模型",
            "precision": "精度",
            "bbox_select": "选择BBox",
            "select_index": "选择编号",
            "cache_model": "缓存模型",
            "individual_objects": "独立物体",
            "mask_preview_color": "遮罩预览颜色",
            "detail_method": "细节处理方法",
            "detail_erode": "细节消融",
            "detail_dilate": "细节膨胀",
            "black_point": "黑色阈值",
            "white_point": "白色阈值",
            "process_detail": "处理细节",
            "device": "设备",
            "max_megapixels": "Vitmatte最大尺寸"
        },
        "outputs": {
            "mask": "遮罩",
            "preview": "预览图像"
        }
    },
    "LayerMask: SegformerUltraV2": {
        "title": "Segformer Ultra V2",
        "inputs": {
            "image": "图像",
            "segformer_pipeline": "Segformer框架"
        },
        "widgets": {
            "detail_method": "细节处理方法",
            "detail_erode": "细节消融",
            "detail_dilate": "细节膨胀",
            "black_point": "黑色阈值",
            "white_point": "白色阈值",
            "process_detail": "处理细节",
            "device": "设备",
            "max_megapixels": "Vitmatte最大尺寸"
        },
        "outputs": {
            "image": "图像",
            "mask": "遮罩"
        }
    },
    "LayerMask: SegformerB2ClothesUltra": {
        "title": "Segformer B2服装 Ultra",
        "inputs": {
            "image": "图像"
        },
        "widgets": {
            "face": "脸",
            "hair": "头发",
            "hat": "帽子",
            "sunglass": "墨镜",
            "left_arm": "左臂",
            "right_arm": "右臂",
            "left_leg": "左腿",
            "right_leg": "右腿",
            "upper_clothes": "上衣",
            "skirt": "短裙",
            "pants": "裤子",
            "dress": "连衣裙",
            "belt": "腰带",
            "shoe": "鞋子",
            "bag": "背包",
            "scarf": "围巾",
            "detail_method": "细节处理方法",
            "detail_erode": "细节消融",
            "detail_dilate": "细节膨胀",
            "black_point": "黑色阈值",
            "white_point": "白色阈值",
            "process_detail": "处理细节",
            "device": "设备",
            "max_megapixels": "Vitmatte最大尺寸"
        },
        "outputs": {
            "image": "图像",
            "mask": "遮罩"
        }
    },
    "LayerMask: SegformerClothesPipelineLoader": {
        "title": "Segformer 服装框架加载器",
        "widgets": {
            "model": "模型",
            "face": "脸",
            "hair": "头发",
            "hat": "帽子",
            "sunglass": "墨镜",
            "left_arm": "左臂",
            "right_arm": "右臂",
            "left_leg": "左腿",
            "right_leg": "右腿",
            "left_shoe": "左鞋",
            "right_shoe": "右鞋",
            "upper_clothes": "上衣",
            "skirt": "短裙",
            "pants": "裤子",
            "dress": "连衣裙",
            "belt": "腰带",
            "bag": "背包",
            "scarf": "围巾"
        },
        "outputs": {
            "segformer_pipeline": "Segformer框架"
        }
    },
    "LayerMask: SegformerFashionPipelineLoader": {
        "title": "Segformer 服饰框架加载器",
        "widgets": {
            "model": "模型",
            "shirt":"衬衫、罩衫",
            "top":"上衣、t恤",
            "sweater":"毛衣",
            "cardigan":"开襟毛衫",
            "jacket":"夹克",
            "vest":"背心",
            "pants":"裤子",
            "shorts":"短裤",
            "skirt":"裙子",
            "coat":"外套",
            "dress":"连衣裙",
            "jumpsuit":"连身裤",
            "cape":"斗篷",
            "glasses":"眼镜",
            "hat":"帽子",
            "hairaccessory":"头带",
            "tie":"领带",
            "glove":"手套",
            "watch":"手表",
            "belt":"皮带",
            "legwarmer":"腿套",
            "tights":"裤袜",
            "sock":"袜子",
            "shoe":"鞋子",
            "bagwallet":"手包",
            "scarf":"围巾",
            "umbrella":"雨伞",
            "hood":"兜帽",
            "collar":"衣领",
            "lapel":"翻领",
            "epaulette":"肩章",
            "sleeve":"袖子",
            "pocket":"口袋",
            "neckline":"领口",
            "buckle":"带扣",
            "zipper":"拉链",
            "applique":"贴花",
            "bead":"珠子",
            "bow":"蝴蝶结",
            "flower":"花",
            "fringe":"刘海",
            "ribbon":"丝带",
            "rivet":"铆钉",
            "ruffle":"褶饰",
            "sequin":"亮片",
            "tassel":"流苏"
        },
        "outputs": {
            "segformer_pipeline": "Segformer框架"
        }
    },
    "LayerMask: SegmentAnythingUltra": {
        "title": "SegmentAnything Ultra",
        "inputs": {
            "image": "图像"
        },
        "widgets": {
            "sam_model": "SAM模型",
            "grounding_dino_model": "GroundingDINO模型",
            "threshold": "阈值",
            "detail_range": "细节范围",
            "black_point": "黑色阈值",
            "white_point": "白色阈值",
            "process_detail": "处理细节",
            "prompt": "提示词"
        },
        "outputs": {
            "image": "图像",
            "mask": "遮罩"
        }
    },
    "LayerMask: SegmentAnythingUltra V2": {
        "title": "SegmentAnything Ultra V2",
        "inputs": {
            "image": "图像"
        },
        "widgets": {
            "sam_model": "SAM模型",
            "grounding_dino_model": "GroundingDINO模型",
            "threshold": "阈值",
            "detail_method": "细节处理方法",
            "detail_erode": "细节消融",
            "detail_dilate": "细节膨胀",
            "black_point": "黑色阈值",
            "white_point": "白色阈值",
            "process_detail": "处理细节",
            "prompt": "提示词",
            "device": "设备",
            "max_megapixels": "Vitmatte最大尺寸"
        },
        "outputs": {
            "image": "图像",
            "mask": "遮罩"
        }
    },
    "LayerMask: Shadow & Highlight Mask": {
        "title": "阴影与高光遮罩",
        "inputs": {
            "image": "图像",
            "mask": "遮罩"
        },
        "widgets": {
            "shadow_level_offset": "阴影强度",
            "shadow_range": "阴影范围",
            "highlight_level_offset": "高光强度",
            "highlight_range": "高光范围"
        },
        "outputs": {
            "shadow_mask": "阴影遮罩",
            "highlight_mask": "高光遮罩"
        }
    },
    "LayerMask: TransparentBackgroundUltra": {
        "title": "透明背景 Ultra",
        "inputs": {
            "image": "图像"
        },
        "widgets": {
            "model": "模型",
            "detail_method": "细节处理方法",
            "detail_erode": "细节消融",
            "detail_dilate": "细节膨胀",
            "black_point": "黑色阈值",
            "white_point": "白色阈值",
            "process_detail": "处理细节",
            "device": "设备",
            "max_megapixels": "Vitmatte最大尺寸"
        },
        "outputs": {
            "image": "图像",
            "mask": "遮罩"
        }
    },
    "LayerMask: YoloV8Detect": {
        "title": "YoloV8检测",
        "inputs": {
            "image": "图像"
        },
        "widgets": {
            "yolo_model": "Yolo模型",
            "mask_merge": "融合遮罩"
        },
        "outputs": {
            "mask": "遮罩",
            "yolo_plot_image": "Yolo预览图像",
            "yolo_masks": "Yolo遮罩"
        }
    }
}
