{
    "BrushNetLoader": {
        "title": "BrushNet加载器",
        "widgets": {
            "brushnet": "BrushNet"
        },
        "outputs": {
            "brushnet": "BrushNet"
        }
    },
    "BrushNetPipeline": {
        "title": "BrushNet节点束",
        "inputs": {
            "model": "模型",
            "clip": "CLIP",
            "vae": "VAE",
            "brushnet": "BrushNet"
        },
        "outputs": {
            "BRPL": "BrushNet节点束"
        }
    },
    "BrushNetInpaint": {
        "title": "BrushNet局部重绘",
        "inputs": {
            "BRPL": "BrushNet节点束",
            "image": "图像",
            "mask": "遮罩",
            "positive": "正面条件",
            "negative": "负面条件"
        },
        "widgets": {
            "seed": "随机种",
            "control_before_generate": "运行前操作",
            "steps": "步数",
            "scale": "缩放"
        },
        "outputs": {
            "image": "图像"
        }
    },
    "BlendInpaint": {
        "title": "混合局部重绘",
        "inputs": {
            "image1": "图像_1",
            "image2": "图像_2",
            "mask": "遮罩"
        },
        "widgets": {
            "blur": "模糊"
        },
        "outputs": {
            "image": "图像"
        }
    }
}